aws_stash/Output.py
aws_stash/ParamStore.py
aws_stash/__init__.py
aws_stash/__main__.py
aws_stash-0.0.9.dist-info/LICENSE
aws_stash-0.0.9.dist-info/METADATA
aws_stash-0.0.9.dist-info/WHEEL
aws_stash-0.0.9.dist-info/entry_points.txt
aws_stash-0.0.9.dist-info/top_level.txt
aws_stash-0.0.9.dist-info/RECORD
