Metadata-Version: 2.1
Name: aws-stash
Version: 0.0.9
Summary: Manage AWS Parameter Store
Home-page: https://github.com/askainet/aws-stash
Author: Ivan Lopez
Author-email: ivan@askai.net
License: UNKNOWN
Platform: UNKNOWN
Classifier: Programming Language :: Python :: 3
Classifier: License :: OSI Approved :: MIT License
Classifier: Operating System :: OS Independent
Requires-Dist: boto3 (>=1.7.38)
Requires-Dist: pyperclip (==1.6.4)
